code/__init__.py
code/x.py
testbrojct2-0.4.dist-info/LICENSE.txt
testbrojct2-0.4.dist-info/METADATA
testbrojct2-0.4.dist-info/WHEEL
testbrojct2-0.4.dist-info/top_level.txt
testbrojct2-0.4.dist-info/RECORD
