Metadata-Version: 2.1
Name: testbrojct2
Version: 0.4
Summary: Sexy liday
Home-page: UNKNOWN
Author: ،NiK
Author-email: UNKNOWN
License: UNKNOWN
Platform: UNKNOWN
Classifier: Programming Language :: Python :: 3
Classifier: Operating System :: OS Independent
Requires-Dist: requests
